model_munger/__init__.py
model_munger/cli.py
model_munger/cloudnet.py
model_munger/download.py
model_munger/extract.py
model_munger/grid.py
model_munger/level.py
model_munger/merge.py
model_munger/metadata.py
model_munger/model.py
model_munger/py.typed
model_munger/utils.py
model_munger/version.py
model_munger/extractors/ecmwf_open.py
model_munger/extractors/gdas1.py
model_munger/readers/__init__.py
model_munger/readers/arpege.py
model_munger/readers/ecmwf_open.py
model_munger/readers/gdas1.py
model_munger-0.3.3.dist-info/METADATA
model_munger-0.3.3.dist-info/WHEEL
model_munger-0.3.3.dist-info/entry_points.txt
model_munger-0.3.3.dist-info/licenses/LICENSE
model_munger-0.3.3.dist-info/RECORD
