Metadata-Version: 2.4
Name: model_munger
Version: 0.3.3
Summary: Extract vertical profiles from NWP models and output netCDF files
Project-URL: Homepage, https://github.com/actris-cloudnet/model-munger
Project-URL: Issues, https://github.com/actris-cloudnet/model-munger/issues
Author-email: Tuomas Siipola <tuomas.siipola@fmi.fi>
License-File: LICENSE
Classifier: Development Status :: 3 - Alpha
Classifier: Intended Audience :: Science/Research
Classifier: License :: OSI Approved :: MIT License
Classifier: Operating System :: OS Independent
Classifier: Programming Language :: Python :: 3
Classifier: Topic :: Scientific/Engineering :: Atmospheric Science
Requires-Python: >=3.10
Requires-Dist: cloudnet-api-client
Requires-Dist: netcdf4
Requires-Dist: pygrib
Requires-Dist: requests
Requires-Dist: scipy
Provides-Extra: dev
Requires-Dist: pre-commit; extra == 'dev'
Requires-Dist: release-version; extra == 'dev'
Provides-Extra: test
Requires-Dist: mypy; extra == 'test'
Requires-Dist: pytest; extra == 'test'
Requires-Dist: ruff; extra == 'test'
Requires-Dist: scipy-stubs; extra == 'test'
Requires-Dist: types-requests; extra == 'test'
